pypixel/Client.py
pypixel/Player.py
pypixel/Skyblock.py
pypixel/__init__.py
mcpy_pixel-0.0.1.dist-info/LICENSE
mcpy_pixel-0.0.1.dist-info/METADATA
mcpy_pixel-0.0.1.dist-info/WHEEL
mcpy_pixel-0.0.1.dist-info/top_level.txt
mcpy_pixel-0.0.1.dist-info/RECORD
