Metadata-Version: 2.1
Name: mcpy-pixel
Version: 0.0.1
Summary: A Simple Python Wrapper for the Minecraft Hypixel API!
Home-page: https://github.com/savagedevelops/pypixelapi
Author: Savage Development
Author-email: support@savagedevelopment.tk
License: MIT
Project-URL: Savage Development, https://www.savagedevelopment.tk
Project-URL: Bug Tracker, https://github.com/savagedevelops/pypixelapi/issues
Keywords: hypixel
Platform: UNKNOWN
Classifier: Development Status :: 1 - Planning
Classifier: Intended Audience :: Developers
Classifier: Operating System :: Microsoft :: Windows :: Windows 10
Classifier: License :: OSI Approved :: MIT License
Classifier: Programming Language :: Python :: 3
Requires-Python: >=3.7
License-File: LICENSE
Requires-Dist: requests
